stix_shifter_modules/aws_cloud_watch_logs/__init__.py
stix_shifter_modules/aws_cloud_watch_logs/entry_point.py
stix_shifter_modules/aws_cloud_watch_logs/configuration/config.json
stix_shifter_modules/aws_cloud_watch_logs/configuration/dialects.json
stix_shifter_modules/aws_cloud_watch_logs/configuration/lang_en.json
stix_shifter_modules/aws_cloud_watch_logs/stix_translation/__init__.py
stix_shifter_modules/aws_cloud_watch_logs/stix_translation/json_to_stix_translator.py
stix_shifter_modules/aws_cloud_watch_logs/stix_translation/query_constructor.py
stix_shifter_modules/aws_cloud_watch_logs/stix_translation/query_translator.py
stix_shifter_modules/aws_cloud_watch_logs/stix_translation/transformers.py
stix_shifter_modules/aws_cloud_watch_logs/stix_translation/json/common_attributes.json
stix_shifter_modules/aws_cloud_watch_logs/stix_translation/json/guardduty_from_stix_map.json
stix_shifter_modules/aws_cloud_watch_logs/stix_translation/json/master_config.json
stix_shifter_modules/aws_cloud_watch_logs/stix_translation/json/network_protocol_map.json
stix_shifter_modules/aws_cloud_watch_logs/stix_translation/json/operators.json
stix_shifter_modules/aws_cloud_watch_logs/stix_translation/json/to_stix_map.json
stix_shifter_modules/aws_cloud_watch_logs/stix_translation/json/vpcflow_from_stix_map.json
stix_shifter_modules/aws_cloud_watch_logs/stix_transmission/__init__.py
stix_shifter_modules/aws_cloud_watch_logs/stix_transmission/boto3_client.py
stix_shifter_modules/aws_cloud_watch_logs/stix_transmission/delete_connector.py
stix_shifter_modules/aws_cloud_watch_logs/stix_transmission/error_mapper.py
stix_shifter_modules/aws_cloud_watch_logs/stix_transmission/ping_connector.py
stix_shifter_modules/aws_cloud_watch_logs/stix_transmission/query_connector.py
stix_shifter_modules/aws_cloud_watch_logs/stix_transmission/results_connector.py
stix_shifter_modules/aws_cloud_watch_logs/stix_transmission/status_connector.py
stix_shifter_modules_aws_cloud_watch_logs-8.0.2.dist-info/licenses/AUTHORS.md
stix_shifter_modules_aws_cloud_watch_logs-8.0.2.dist-info/licenses/LICENSE.md
stix_shifter_modules_aws_cloud_watch_logs-8.0.2.dist-info/licenses/NOTICE
stix_shifter_modules_aws_cloud_watch_logs-8.0.2.dist-info/METADATA
stix_shifter_modules_aws_cloud_watch_logs-8.0.2.dist-info/WHEEL
stix_shifter_modules_aws_cloud_watch_logs-8.0.2.dist-info/top_level.txt
stix_shifter_modules_aws_cloud_watch_logs-8.0.2.dist-info/RECORD
